MANIFEST.in
requirements.txt
setup.py
bin/xos-migrate
xosmigrate/VERSION
xosmigrate/__init__.py
xosmigrate/main.py
xosmigrate/migration_cfg.yaml
xosmigrate/migration_cfg_schema.yaml
xosmigrate.egg-info/PKG-INFO
xosmigrate.egg-info/SOURCES.txt
xosmigrate.egg-info/dependency_links.txt
xosmigrate.egg-info/requires.txt
xosmigrate.egg-info/top_level.txt