Metadata-Version: 1.1
Name: xosmigrate
Version: 3.2.1
Summary: XOS Migrations Toolkit
Home-page: UNKNOWN
Author: Matteo Scandolo
Author-email: teo@opennetworking.org
License: Apache v2
Platform: UNKNOWN
Classifier: License :: OSI Approved :: Apache Software License
